ailab_utils/__init__.py
ailab_utils/__version__.py
ailab_utils/logger.py
ailab_utils-0.1.3.dist-info/LICENSE
ailab_utils-0.1.3.dist-info/METADATA
ailab_utils-0.1.3.dist-info/WHEEL
ailab_utils-0.1.3.dist-info/top_level.txt
ailab_utils-0.1.3.dist-info/RECORD
